yakka/__init__.py
yakka/binding.py
yakka/bucket.py
yakka/folder.py
yakka/function.py
yakka/generated/spec.ts
yakka/globals.py
yakka/integration.py
yakka/memoize.py
yakka/queue.py
yakka/reflect.py
yakka/resource.py
yakka/spec.py
yakka/synth-aws-cdk.ts
yakka/synth.py
yakka-0.1.0.dist-info/METADATA
yakka-0.1.0.dist-info/WHEEL
yakka-0.1.0.dist-info/RECORD
