Metadata-Version: 2.1
Name: yakka
Version: 0.1.0
Summary: Infrastructure for AI applications and machine learning pipelines
Author: sam
Author-email: sam@eventual.ai
Requires-Python: ==3.12.1
Classifier: Programming Language :: Python :: 3
Requires-Dist: aiobotocore (>=2.9.0,<3.0.0)
Requires-Dist: botocore (>=1.33.2,<1.33.14)
Requires-Dist: pydantic (>=2.5.3,<3.0.0)
